{
  "type": "minecraft:crafting_shaped",
  "conditions": [
    {
      "type": "spartanweaponry:type_disabled",
      "disabled": [
        "heavy_crossbow",
        "bronze"
      ]
    },
    {
      "type": "forge:not",
      "value": {
        "type": "forge:tag_empty",
        "tag": "forge:ingots/bronze"
      }
    }
  ],
  "group": "spartanweaponry:heavy_crossbow",
  "key": {
    "#": {
      "tag": "forge:ingots/bronze"
    },
    "D": {
      "item": "minecraft:bow"
    },
    "H": {
      "item": "minecraft:tripwire_hook"
    },
    "P": {
      "tag": "minecraft:planks"
    },
    "|": {
      "item": "spartanweaponry:handle"
    }
  },
  "pattern": [
    "#D#",
    "PHP",
    " | "
  ],
  "result": {
    "item": "spartanweaponry:bronze_heavy_crossbow"
  }
}