{
  "type": "minecraft:crafting_shaped",
  "group": "spartanweaponry:greatsword",
  "pattern": [
    " # ",
    "###",
    "#|#"
  ],
  "key": {
    "#": {
      "tag": "forge:ingots/copper"
    },
    "|": {
      "item": "spartanweaponry:handle"
    }
  },
  "result": {
    "item": "spartanweaponry:copper_greatsword"
  },
  "conditions": [
    {
      "disabled": [
        "greatsword",
        "copper"
      ],
      "type": "spartanweaponry:type_disabled"
    },
    {
      "value": {
        "tag": "forge:ingots/copper",
        "type": "forge:tag_empty"
      },
      "type": "forge:not"
    }
  ]
}