{
  "type": "minecraft:crafting_shaped",
  "conditions": [
    {
      "type": "spartanweaponry:type_disabled",
      "disabled": [
        "spear",
        "copper"
      ]
    },
    {
      "type": "forge:not",
      "value": {
        "type": "forge:tag_empty",
        "tag": "forge:ingots/copper"
      }
    }
  ],
  "group": "spartanweaponry:spear",
  "key": {
    "#": {
      "tag": "forge:ingots/copper"
    },
    "/": {
      "tag": "spartanweaponry:poles"
    }
  },
  "pattern": [
    "#",
    "/"
  ],
  "result": {
    "item": "spartanweaponry:copper_spear"
  }
}