{
  "type": "minecraft:crafting_shaped",
  "group": "spartanweaponry:longbow",
  "pattern": [
    "|/#",
    "/ ~",
    "#~~"
  ],
  "key": {
    "#": {
      "tag": "forge:ingots/invar"
    },
    "|": {
      "item": "spartanweaponry:handle"
    },
    "/": {
      "tag": "forge:rods/wooden"
    },
    "~": {
      "tag": "forge:string"
    }
  },
  "result": {
    "item": "spartanweaponry:invar_longbow"
  },
  "conditions": [
    {
      "disabled": [
        "longbow",
        "invar"
      ],
      "type": "spartanweaponry:type_disabled"
    },
    {
      "value": {
        "tag": "forge:ingots/invar",
        "type": "forge:tag_empty"
      },
      "type": "forge:not"
    }
  ]
}